autoclasstoc/__init__.py
autoclasstoc/errors.py
autoclasstoc/nodes.py
autoclasstoc/plugin.py
autoclasstoc/sections.py
autoclasstoc/utils.py
autoclasstoc/_static/autoclasstoc.css
autoclasstoc-1.7.0.dist-info/WHEEL
autoclasstoc-1.7.0.dist-info/METADATA
autoclasstoc-1.7.0.dist-info/RECORD
