Metadata-Version: 2.1
Name: autoclasstoc
Version: 1.7.0
Summary: Add a succinct TOC to auto-documented classes.
Author-email: Kale Kundert <kale@thekunderts.net>
Requires-Python: >=3.6
Classifier: Programming Language :: Python :: 3
Requires-Dist: sphinx>=3.0
Requires-Dist: docutils
Requires-Dist: more_itertools
Requires-Dist: sphinx>=3.1 ; extra == "docs"
Requires-Dist: sphinx_rtd_theme ; extra == "docs"
Requires-Dist: pytest ; extra == "tests"
Requires-Dist: parametrize_from_file ; extra == "tests"
Requires-Dist: re_assert ; extra == "tests"
Requires-Dist: pytest_tmp_files ; extra == "tests"
Requires-Dist: lxml ; extra == "tests"
Requires-Dist: coverage[toml] ; extra == "tests"
Requires-Dist: coverage_enable_subprocess ; extra == "tests"
Requires-Dist: tox ; extra == "tests"
Project-URL: Bug Tracker, https://github.com/kalekundert/autoclasstoc/issues
Project-URL: Continuous Integration, https://github.com/kalekundert/autoclasstoc/actions
Project-URL: Documentation, https://autoclasstoc.readthedocs.io/en/latest/
Project-URL: Test Coverage, https://coveralls.io/github/kalekundert/autoclasstoc
Project-URL: Version Control, https://github.com/kalekundert/autoclasstoc
Provides-Extra: docs
Provides-Extra: tests
